AUTHORS
LICENSE
MANIFEST.in
README.rst
setup.cfg
setup.py
django_healthpoint.egg-info/PKG-INFO
django_healthpoint.egg-info/SOURCES.txt
django_healthpoint.egg-info/dependency_links.txt
django_healthpoint.egg-info/not-zip-safe
django_healthpoint.egg-info/requires.txt
django_healthpoint.egg-info/top_level.txt
healthpoint/__init__.py
healthpoint/decorators.py
healthpoint/registry.py
healthpoint/urls.py
healthpoint/views.py
healthpoint/tests/__init__.py
healthpoint/tests/health.py
healthpoint/tests/settings.py
healthpoint/tests/test_views.py
healthpoint/tests/urls.py